{"contestName":"AUG17","contestQuestion":"MATDW","time":{"1502315828":[],"1502319616":{"C":2,"C++ 6.3":1,"C++14":5,"JAVA":2},"1502321656":{"C":2,"C++ 6.3":1,"C++14":5,"JAVA":2},"1502358765":{"C":3,"C++ 6.3":1,"C++14":12,"JAVA":4},"1502366632":{"C":3,"C++ 6.3":1,"C++14":13,"JAVA":4},"1502392918":{"C":4,"C++ 6.3":2,"C++14":22,"JAVA":6},"1502396321":{"C":4,"C++ 6.3":2,"C++14":22,"JAVA":6},"1502431880":{"C":4,"C++ 6.3":3,"C++14":22,"JAVA":6},"1502431907":{"C":4,"C++ 6.3":3,"C++14":22,"JAVA":6},"1502461938":{"C":4,"C++ 6.3":4,"C++14":31,"JAVA":8,"C++ 4.3.2":1},"1502476107":{"C":4,"C++ 6.3":5,"C++14":32,"JAVA":10,"C++ 4.3.2":1},"1502547196":{"C":4,"C++ 6.3":7,"C++14":42,"JAVA":14,"C++ 4.3.2":2,"PYTH":1,"PYTH 3.5":1},"1502547424":{"C":4,"C++ 6.3":7,"C++14":42,"JAVA":14,"C++ 4.3.2":2,"PYTH":1,"PYTH 3.5":1},"1502612418":{"C":4,"C++ 6.3":8,"C++14":43,"JAVA":16,"C++ 4.3.2":2,"PYTH":1,"PYTH 3.5":1},"1502622672":{"C":4,"C++ 6.3":9,"C++14":44,"JAVA":18,"C++ 4.3.2":2,"PYTH":1,"PYTH 3.5":1},"1502628432":{"C":4,"C++ 6.3":10,"C++14":45,"JAVA":20,"C++ 4.3.2":2,"PYTH":1,"PYTH 3.5":1},"1502649925":{"C":4,"C++ 6.3":11,"C++14":46,"JAVA":25,"C++ 4.3.2":2,"PYTH":1,"PYTH 3.5":1},"1502689285":{"C":4,"C++ 6.3":12,"C++14":47,"JAVA":27,"C++ 4.3.2":2,"PYTH":1,"PYTH 3.5":1},"1502737470":{"C":4,"C++ 6.3":12,"C++14":48,"JAVA":35,"C++ 4.3.2":2,"PYTH":2,"PYTH 3.5":2},"1502737910":{"C":4,"C++ 6.3":12,"C++14":48,"JAVA":35,"C++ 4.3.2":2,"PYTH":2,"PYTH 3.5":2},"1502737914":{"C":4,"C++ 6.3":12,"C++14":48,"JAVA":35,"C++ 4.3.2":2,"PYTH":2,"PYTH 3.5":2},"1502738523":{"C":4,"C++ 6.3":12,"C++14":48,"JAVA":36,"C++ 4.3.2":2,"PYTH":2,"PYTH 3.5":2},"1502789788":{"C":4,"C++ 6.3":12,"C++14":50,"JAVA":43,"C++ 4.3.2":2,"PYTH":2,"PYTH 3.5":3},"1502789839":{"C":4,"C++ 6.3":12,"C++14":50,"JAVA":43,"C++ 4.3.2":2,"PYTH":2,"PYTH 3.5":3},"1502901334":{"C":4,"C++ 6.3":13,"C++14":58,"JAVA":51,"C++ 4.3.2":3,"PYTH":3,"PYTH 3.5":4},"1503232796":{"C":5,"C++ 6.3":24,"C++14":94,"JAVA":60,"C++ 4.3.2":4,"PYTH":4,"PYTH 3.5":4},"1503233058":{"C":5,"C++ 6.3":24,"C++14":94,"JAVA":60,"C++ 4.3.2":4,"PYTH":4,"PYTH 3.5":4},"1503233085":{"C":5,"C++ 6.3":24,"C++14":94,"JAVA":60,"C++ 4.3.2":4,"PYTH":4,"PYTH 3.5":4}},"pointer":{"1502315828":{"page":0,"line":0},"1502319616":{"page":1,"line":11},"1502321656":{"page":1,"line":11},"1502358765":{"page":2,"line":9},"1502366632":{"page":2,"line":10},"1502392918":{"page":3,"line":11},"1502396321":{"page":3,"line":11},"1502431880":{"page":3,"line":12},"1502431907":{"page":3,"line":12},"1502461938":{"page":4,"line":1},"1502476107":{"page":5,"line":5},"1502547196":{"page":6,"line":12},"1502547424":{"page":6,"line":12},"1502612418":{"page":7,"line":4},"1502622672":{"page":7,"line":8},"1502628432":{"page":7,"line":12},"1502649925":{"page":8,"line":7},"1502689285":{"page":8,"line":11},"1502737470":{"page":9,"line":10},"1502737910":{"page":9,"line":10},"1502737914":{"page":9,"line":10},"1502738523":{"page":9,"line":11},"1502789788":{"page":10,"line":9},"1502789839":{"page":10,"line":9},"1502901334":{"page":12,"line":5},"1503232796":{"page":17,"line":4},"1503233058":{"page":17,"line":4},"1503233085":{"page":17,"line":4}}}